{
  "functions": [
    {
      "cfg": {
        "edges": [
          {
            "from": "b0",
            "to": "b1"
          },
          {
            "from": "b1",
            "to": "b7"
          },
          {
            "from": "b1",
            "to": "b2"
          },
          {
            "from": "b2",
            "to": "b3"
          },
          {
            "from": "b3",
            "to": "b6"
          },
          {
            "from": "b3",
            "to": "b4"
          },
          {
            "from": "b4",
            "to": "b5"
          },
          {
            "from": "b5",
            "to": "b3"
          },
          {
            "from": "b6",
            "to": "b1"
          }
        ],
        "nodes": [
          {
            "cost": 2,
            "id": "b0",
            "impact": 2,
            "instructions": {
              "arith": 0,
              "branch": 1,
              "memory": 0,
              "other": 0,
              "total": 1
            },
            "label": "entry"
          },
          {
            "cost": 4,
            "id": "b1",
            "impact": 400,
            "instructions": {
              "arith": 1,
              "branch": 1,
              "memory": 0,
              "other": 1,
              "total": 3
            },
            "label": "outer"
          },
          {
            "cost": 2,
            "id": "b2",
            "impact": 200,
            "instructions": {
              "arith": 0,
              "branch": 1,
              "memory": 0,
              "other": 0,
              "total": 1
            },
            "label": "inner_entry"
          },
          {
            "cost": 7,
            "id": "b3",
            "impact": 70000,
            "instructions": {
              "arith": 4,
              "branch": 1,
              "memory": 0,
              "other": 1,
              "total": 6
            },
            "label": "inner"
          },
          {
            "cost": 25,
            "id": "b4",
            "impact": 250000,
            "instructions": {
              "arith": 1,
              "branch": 1,
              "memory": 3,
              "other": 0,
              "total": 5
            },
            "label": "body"
          },
          {
            "cost": 3,
            "id": "b5",
            "impact": 30000,
            "instructions": {
              "arith": 1,
              "branch": 1,
              "memory": 0,
              "other": 0,
              "total": 2
            },
            "label": "inner_step"
          },
          {
            "cost": 3,
            "id": "b6",
            "impact": 300,
            "instructions": {
              "arith": 1,
              "branch": 1,
              "memory": 0,
              "other": 0,
              "total": 2
            },
            "label": "outer_inc"
          },
          {
            "cost": 2,
            "id": "b7",
            "impact": 2,
            "instructions": {
              "arith": 0,
              "branch": 1,
              "memory": 0,
              "other": 0,
              "total": 1
            },
            "label": "exit"
          }
        ]
      },
      "instruction_count": 21,
      "loops": [
        {
          "blocks": [
            "outer",
            "inner_entry",
            "inner",
            "body",
            "inner_step",
            "outer_inc"
          ],
          "critical_path": [
            "inner",
            "body",
            "inner_step"
          ],
          "dependencies": [],
          "depth": 1,
          "header": "outer",
          "id": "tile_demo::outer::0",
          "induction_variable": "",
          "memory_accesses": [],
          "trip_count": "unknown"
        },
        {
          "blocks": [
            "inner",
            "body",
            "inner_step"
          ],
          "critical_path": [
            "inner",
            "body",
            "inner_step"
          ],
          "dependencies": [],
          "depth": 2,
          "header": "inner",
          "id": "tile_demo::inner::1",
          "induction_variable": "",
          "memory_accesses": [],
          "trip_count": "unknown"
        }
      ],
      "name": "tile_demo"
    }
  ]
}
